target_synthesis_agent/__init__.py
target_synthesis_agent/agent.py
target_synthesis_agent/cli.py
target_synthesis_agent/config.py
target_synthesis_agent/constants.py
target_synthesis_agent/models.py
target_synthesis_agent/utils.py
target_synthesis_agent-1.0.12.dist-info/METADATA
target_synthesis_agent-1.0.12.dist-info/WHEEL
target_synthesis_agent-1.0.12.dist-info/entry_points.txt
target_synthesis_agent-1.0.12.dist-info/top_level.txt
target_synthesis_agent-1.0.12.dist-info/RECORD
