Metadata-Version: 2.4
Name: target-synthesis-agent
Version: 1.0.12
Summary: AI-powered target variable creation and synthesis agent
Author-email: StepFunction AI <team@stepfunction.ai>
Maintainer-email: StepFunction AI <team@stepfunction.ai>
License-Expression: MIT
Project-URL: Homepage, https://github.com/stepfnAI/target_synthesis_agent
Project-URL: Documentation, https://github.com/stepfnAI/target_synthesis_agent#readme
Project-URL: Repository, https://github.com/stepfnAI/target_synthesis_agent.git
Project-URL: Bug Tracker, https://github.com/stepfnAI/target_synthesis_agent/issues
Requires-Python: >=3.11
Requires-Dist: sfn-blueprint>=0.6.6
Requires-Dist: pandas>=1.5.0
Requires-Dist: numpy>=1.21.0
Requires-Dist: pydantic>=2.0.0
Requires-Dist: scikit-learn>=1.5.2
Requires-Dist: numba>=0.57.0
Requires-Dist: llvmlite>=0.40.0
Requires-Dist: shap>=0.45.0
Provides-Extra: dev
Requires-Dist: pytest>=7.0.0; extra == "dev"
Requires-Dist: pytest-cov>=4.0.0; extra == "dev"
Requires-Dist: pytest-asyncio>=0.20.0; extra == "dev"
Requires-Dist: black>=22.0.0; extra == "dev"
Requires-Dist: flake8>=5.0.0; extra == "dev"
Requires-Dist: mypy>=1.0.0; extra == "dev"
Provides-Extra: test
Requires-Dist: pytest>=7.0.0; extra == "test"
Requires-Dist: pytest-cov>=4.0.0; extra == "test"
Requires-Dist: pytest-asyncio>=0.20.0; extra == "test"
